zlepy/__about__.py
zlepy/__init__.py
zlepy/eigs.py
zlepy/fgen.py
zlepy/gen.py
zlepy-0.3.2.dist-info/METADATA
zlepy-0.3.2.dist-info/WHEEL
zlepy-0.3.2.dist-info/licenses/LICENSE
zlepy-0.3.2.dist-info/RECORD
