Metadata-Version: 2.3
Name: zlepy
Version: 0.3.2
Summary: Toolkit for integer-linear-eigenvalue matrix generation and evaluation.
Project-URL: Homepage, https://github.com/symeig/zle-py
Project-URL: Issues, https://github.com/symeig/zle-py/issues
Author-email: Abraham Miller <abraham.r.m@gmail.com>, Jonny Luntzel <jonny9860@gmail.com>
License-Expression: Apache-2.0
License-File: LICENSE
Keywords: eigenvalue,integer-linear eigenvalues,interpretable spectra,linear algebra,matrix
Classifier: License :: OSI Approved :: Apache Software License
Classifier: Operating System :: OS Independent
Classifier: Programming Language :: Python
Classifier: Programming Language :: Python :: 3.8
Classifier: Programming Language :: Python :: 3.9
Classifier: Programming Language :: Python :: 3.10
Classifier: Programming Language :: Python :: 3.11
Classifier: Programming Language :: Python :: 3.12
Requires-Python: >=3.8
Requires-Dist: mpmath
Requires-Dist: numpy
Requires-Dist: sympy
